[
  {
    "ContainingType": "HouseRentWebApi.Controllers.AccountController",
    "Method": "Login",
    "RelativePath": "api/Account/Login",
    "HttpMethod": "POST",
    "IsController": true,
    "Order": 0,
    "Parameters": [
      {
        "Name": "command",
        "Type": "HouseRentWebApi.ApplicationLogic.AccountLogic.Command.LoginCommand",
        "IsRequired": true
      }
    ],
    "ReturnTypes": [
      {
        "Type": "HouseRentWebApi.ApplicationLogic.AccountLogic.Model.UserModel",
        "MediaTypes": [
          "text/plain",
          "application/json",
          "text/json"
        ],
        "StatusCode": 200
      },
      {
        "Type": "Microsoft.AspNetCore.Mvc.ProblemDetails",
        "MediaTypes": [
          "text/plain",
          "application/json",
          "text/json"
        ],
        "StatusCode": 0
      }
    ]
  },
  {
    "ContainingType": "HouseRentWebApi.Controllers.AccountController",
    "Method": "Registration",
    "RelativePath": "api/Account/Registration",
    "HttpMethod": "POST",
    "IsController": true,
    "Order": 0,
    "Parameters": [
      {
        "Name": "command",
        "Type": "HouseRentWebApi.ApplicationLogic.AccountLogic.Command.RegistrationCommand",
        "IsRequired": true
      }
    ],
    "ReturnTypes": [
      {
        "Type": "HouseRentWebApi.ApplicationLogic.AccountLogic.Model.UserModel",
        "MediaTypes": [
          "text/plain",
          "application/json",
          "text/json"
        ],
        "StatusCode": 200
      },
      {
        "Type": "Microsoft.AspNetCore.Mvc.ProblemDetails",
        "MediaTypes": [
          "text/plain",
          "application/json",
          "text/json"
        ],
        "StatusCode": 0
      }
    ]
  },
  {
    "ContainingType": "HouseRentWebApi.Controllers.AddressController",
    "Method": "Delete",
    "RelativePath": "api/Address/Delete/{id}",
    "HttpMethod": "GET",
    "IsController": true,
    "Order": 0,
    "Parameters": [
      {
        "Name": "id",
        "Type": "System.Int32",
        "IsRequired": true
      }
    ],
    "ReturnTypes": [
      {
        "Type": "System.Int32",
        "MediaTypes": [
          "text/plain",
          "application/json",
          "text/json"
        ],
        "StatusCode": 200
      }
    ]
  },
  {
    "ContainingType": "HouseRentWebApi.Controllers.AddressController",
    "Method": "Get",
    "RelativePath": "api/Address/Get/{id}",
    "HttpMethod": "GET",
    "IsController": true,
    "Order": 0,
    "Parameters": [
      {
        "Name": "id",
        "Type": "System.Int32",
        "IsRequired": true
      }
    ],
    "ReturnTypes": [
      {
        "Type": "HouseRentWebApi.ApplicationLogic.AddressLogic.Model.AddressViewModel",
        "MediaTypes": [
          "text/plain",
          "application/json",
          "text/json"
        ],
        "StatusCode": 200
      },
      {
        "Type": "Microsoft.AspNetCore.Mvc.ProblemDetails",
        "MediaTypes": [
          "text/plain",
          "application/json",
          "text/json"
        ],
        "StatusCode": 404
      }
    ]
  },
  {
    "ContainingType": "HouseRentWebApi.Controllers.AddressController",
    "Method": "GetAll",
    "RelativePath": "api/Address/GetAll",
    "HttpMethod": "GET",
    "IsController": true,
    "Order": 0,
    "Parameters": [],
    "ReturnTypes": [
      {
        "Type": "System.Collections.Generic.ICollection\u00601[[HouseRentWebApi.ApplicationLogic.AddressLogic.Model.AddressGridModel, HouseRentWebApi.ApplicationLogic, Version=1.0.0.0, Culture=neutral, PublicKeyToken=null]]",
        "MediaTypes": [
          "text/plain",
          "application/json",
          "text/json"
        ],
        "StatusCode": 200
      }
    ]
  },
  {
    "ContainingType": "HouseRentWebApi.Controllers.AddressController",
    "Method": "Upsert",
    "RelativePath": "api/Address/Upsert",
    "HttpMethod": "POST",
    "IsController": true,
    "Order": 0,
    "Parameters": [
      {
        "Name": "command",
        "Type": "HouseRentWebApi.ApplicationLogic.AddressLogic.Command.UpsertAddressCommand",
        "IsRequired": true
      }
    ],
    "ReturnTypes": [
      {
        "Type": "System.Int32",
        "MediaTypes": [
          "text/plain",
          "application/json",
          "text/json"
        ],
        "StatusCode": 200
      },
      {
        "Type": "Microsoft.AspNetCore.Mvc.ProblemDetails",
        "MediaTypes": [
          "text/plain",
          "application/json",
          "text/json"
        ],
        "StatusCode": 0
      }
    ]
  },
  {
    "ContainingType": "HouseRentWebApi.Controllers.CityController",
    "Method": "Delete",
    "RelativePath": "api/City/Delete/{id}",
    "HttpMethod": "GET",
    "IsController": true,
    "Order": 0,
    "Parameters": [
      {
        "Name": "id",
        "Type": "System.Int32",
        "IsRequired": true
      }
    ],
    "ReturnTypes": [
      {
        "Type": "System.Int32",
        "MediaTypes": [
          "text/plain",
          "application/json",
          "text/json"
        ],
        "StatusCode": 200
      }
    ]
  },
  {
    "ContainingType": "HouseRentWebApi.Controllers.CityController",
    "Method": "Get",
    "RelativePath": "api/City/Get/{id}",
    "HttpMethod": "GET",
    "IsController": true,
    "Order": 0,
    "Parameters": [
      {
        "Name": "id",
        "Type": "System.Int32",
        "IsRequired": true
      }
    ],
    "ReturnTypes": [
      {
        "Type": "HouseRentWebApi.ApplicationLogic.CityLogic.Model.CityViewModel",
        "MediaTypes": [
          "text/plain",
          "application/json",
          "text/json"
        ],
        "StatusCode": 200
      },
      {
        "Type": "Microsoft.AspNetCore.Mvc.ProblemDetails",
        "MediaTypes": [
          "text/plain",
          "application/json",
          "text/json"
        ],
        "StatusCode": 404
      }
    ]
  },
  {
    "ContainingType": "HouseRentWebApi.Controllers.CityController",
    "Method": "GetAll",
    "RelativePath": "api/City/GetAll",
    "HttpMethod": "GET",
    "IsController": true,
    "Order": 0,
    "Parameters": [],
    "ReturnTypes": [
      {
        "Type": "System.Collections.Generic.ICollection\u00601[[HouseRentWebApi.ApplicationLogic.CityLogic.Model.CityGridModel, HouseRentWebApi.ApplicationLogic, Version=1.0.0.0, Culture=neutral, PublicKeyToken=null]]",
        "MediaTypes": [
          "text/plain",
          "application/json",
          "text/json"
        ],
        "StatusCode": 200
      }
    ]
  },
  {
    "ContainingType": "HouseRentWebApi.Controllers.CityController",
    "Method": "Upsert",
    "RelativePath": "api/City/Upsert",
    "HttpMethod": "POST",
    "IsController": true,
    "Order": 0,
    "Parameters": [
      {
        "Name": "command",
        "Type": "HouseRentWebApi.ApplicationLogic.CityLogic.Command.UpsertCityCommand",
        "IsRequired": true
      }
    ],
    "ReturnTypes": [
      {
        "Type": "System.Int32",
        "MediaTypes": [
          "text/plain",
          "application/json",
          "text/json"
        ],
        "StatusCode": 200
      },
      {
        "Type": "Microsoft.AspNetCore.Mvc.ProblemDetails",
        "MediaTypes": [
          "text/plain",
          "application/json",
          "text/json"
        ],
        "StatusCode": 0
      }
    ]
  },
  {
    "ContainingType": "HouseRentWebApi.Controllers.CountryController",
    "Method": "Delete",
    "RelativePath": "api/Country/Delete/{id}",
    "HttpMethod": "GET",
    "IsController": true,
    "Order": 0,
    "Parameters": [
      {
        "Name": "id",
        "Type": "System.Int32",
        "IsRequired": true
      }
    ],
    "ReturnTypes": [
      {
        "Type": "System.Int32",
        "MediaTypes": [
          "text/plain",
          "application/json",
          "text/json"
        ],
        "StatusCode": 200
      }
    ]
  },
  {
    "ContainingType": "HouseRentWebApi.Controllers.CountryController",
    "Method": "Get",
    "RelativePath": "api/Country/Get/{id}",
    "HttpMethod": "GET",
    "IsController": true,
    "Order": 0,
    "Parameters": [
      {
        "Name": "id",
        "Type": "System.Int32",
        "IsRequired": true
      }
    ],
    "ReturnTypes": [
      {
        "Type": "HouseRentWebApi.ApplicationLogic.CountryLogic.Model.CountryViewModel",
        "MediaTypes": [
          "text/plain",
          "application/json",
          "text/json"
        ],
        "StatusCode": 200
      },
      {
        "Type": "Microsoft.AspNetCore.Mvc.ProblemDetails",
        "MediaTypes": [
          "text/plain",
          "application/json",
          "text/json"
        ],
        "StatusCode": 404
      }
    ]
  },
  {
    "ContainingType": "HouseRentWebApi.Controllers.CountryController",
    "Method": "GetAll",
    "RelativePath": "api/Country/GetAll",
    "HttpMethod": "GET",
    "IsController": true,
    "Order": 0,
    "Parameters": [],
    "ReturnTypes": [
      {
        "Type": "System.Collections.Generic.ICollection\u00601[[HouseRentWebApi.ApplicationLogic.CountryLogic.Model.CountryGridModel, HouseRentWebApi.ApplicationLogic, Version=1.0.0.0, Culture=neutral, PublicKeyToken=null]]",
        "MediaTypes": [
          "text/plain",
          "application/json",
          "text/json"
        ],
        "StatusCode": 200
      }
    ]
  },
  {
    "ContainingType": "HouseRentWebApi.Controllers.CountryController",
    "Method": "Upsert",
    "RelativePath": "api/Country/Upsert",
    "HttpMethod": "POST",
    "IsController": true,
    "Order": 0,
    "Parameters": [
      {
        "Name": "command",
        "Type": "HouseRentWebApi.ApplicationLogic.CountryLogic.Command.UpsertCountryCommand",
        "IsRequired": true
      }
    ],
    "ReturnTypes": [
      {
        "Type": "System.Int32",
        "MediaTypes": [
          "text/plain",
          "application/json",
          "text/json"
        ],
        "StatusCode": 200
      },
      {
        "Type": "Microsoft.AspNetCore.Mvc.ProblemDetails",
        "MediaTypes": [
          "text/plain",
          "application/json",
          "text/json"
        ],
        "StatusCode": 0
      }
    ]
  },
  {
    "ContainingType": "HouseRentWebApi.Controllers.FurnishingTypeController",
    "Method": "Delete",
    "RelativePath": "api/FurnishingType/Delete/{id}",
    "HttpMethod": "DELETE",
    "IsController": true,
    "Order": 0,
    "Parameters": [
      {
        "Name": "id",
        "Type": "System.Int32",
        "IsRequired": true
      }
    ],
    "ReturnTypes": [
      {
        "Type": "System.Int32",
        "MediaTypes": [
          "text/plain",
          "application/json",
          "text/json"
        ],
        "StatusCode": 200
      }
    ]
  },
  {
    "ContainingType": "HouseRentWebApi.Controllers.FurnishingTypeController",
    "Method": "Get",
    "RelativePath": "api/FurnishingType/Get/{id}",
    "HttpMethod": "GET",
    "IsController": true,
    "Order": 0,
    "Parameters": [
      {
        "Name": "id",
        "Type": "System.Int32",
        "IsRequired": true
      }
    ],
    "ReturnTypes": [
      {
        "Type": "HouseRentWebApi.ApplicationLogic.FurnishingTypeLogic.Model.FurnishingTypeViewModel",
        "MediaTypes": [
          "text/plain",
          "application/json",
          "text/json"
        ],
        "StatusCode": 200
      },
      {
        "Type": "Microsoft.AspNetCore.Mvc.ProblemDetails",
        "MediaTypes": [
          "text/plain",
          "application/json",
          "text/json"
        ],
        "StatusCode": 404
      }
    ]
  },
  {
    "ContainingType": "HouseRentWebApi.Controllers.FurnishingTypeController",
    "Method": "GetAll",
    "RelativePath": "api/FurnishingType/GetAll",
    "HttpMethod": "GET",
    "IsController": true,
    "Order": 0,
    "Parameters": [],
    "ReturnTypes": [
      {
        "Type": "System.Collections.Generic.ICollection\u00601[[HouseRentWebApi.ApplicationLogic.FurnishingTypeLogic.Model.FurnishingTypeGridModel, HouseRentWebApi.ApplicationLogic, Version=1.0.0.0, Culture=neutral, PublicKeyToken=null]]",
        "MediaTypes": [
          "text/plain",
          "application/json",
          "text/json"
        ],
        "StatusCode": 200
      }
    ]
  },
  {
    "ContainingType": "HouseRentWebApi.Controllers.FurnishingTypeController",
    "Method": "Upsert",
    "RelativePath": "api/FurnishingType/Upsert",
    "HttpMethod": "POST",
    "IsController": true,
    "Order": 0,
    "Parameters": [
      {
        "Name": "command",
        "Type": "HouseRentWebApi.ApplicationLogic.FurnishingTypeLogic.Command.UpsertFurnishingTypeCommand",
        "IsRequired": true
      }
    ],
    "ReturnTypes": [
      {
        "Type": "System.Int32",
        "MediaTypes": [
          "text/plain",
          "application/json",
          "text/json"
        ],
        "StatusCode": 200
      },
      {
        "Type": "Microsoft.AspNetCore.Mvc.ProblemDetails",
        "MediaTypes": [
          "text/plain",
          "application/json",
          "text/json"
        ],
        "StatusCode": 0
      }
    ]
  },
  {
    "ContainingType": "HouseRentWebApi.Controllers.ImageUploadController",
    "Method": "UploadImage",
    "RelativePath": "api/ImageUpload/UploadImage",
    "HttpMethod": "POST",
    "IsController": true,
    "Order": 0,
    "Parameters": [
      {
        "Name": "formFile",
        "Type": "Microsoft.AspNetCore.Http.IFormFile",
        "IsRequired": false
      },
      {
        "Name": "propertyId",
        "Type": "System.Int32",
        "IsRequired": false
      }
    ],
    "ReturnTypes": []
  },
  {
    "ContainingType": "HouseRentWebApi.Controllers.PropertyController",
    "Method": "Delete",
    "RelativePath": "api/Property/Delete/{id}",
    "HttpMethod": "GET",
    "IsController": true,
    "Order": 0,
    "Parameters": [
      {
        "Name": "id",
        "Type": "System.Int32",
        "IsRequired": true
      }
    ],
    "ReturnTypes": [
      {
        "Type": "System.Int32",
        "MediaTypes": [
          "text/plain",
          "application/json",
          "text/json"
        ],
        "StatusCode": 200
      }
    ]
  },
  {
    "ContainingType": "HouseRentWebApi.Controllers.PropertyController",
    "Method": "Get",
    "RelativePath": "api/Property/Get/{id}",
    "HttpMethod": "GET",
    "IsController": true,
    "Order": 0,
    "Parameters": [
      {
        "Name": "id",
        "Type": "System.Int32",
        "IsRequired": true
      }
    ],
    "ReturnTypes": [
      {
        "Type": "HouseRentWebApi.ApplicationLogic.PropertyLogic.Model.PropertyViewModel",
        "MediaTypes": [
          "text/plain",
          "application/json",
          "text/json"
        ],
        "StatusCode": 200
      },
      {
        "Type": "Microsoft.AspNetCore.Mvc.ProblemDetails",
        "MediaTypes": [
          "text/plain",
          "application/json",
          "text/json"
        ],
        "StatusCode": 404
      }
    ]
  },
  {
    "ContainingType": "HouseRentWebApi.Controllers.PropertyController",
    "Method": "GetAll",
    "RelativePath": "api/Property/GetAll",
    "HttpMethod": "GET",
    "IsController": true,
    "Order": 0,
    "Parameters": [],
    "ReturnTypes": [
      {
        "Type": "System.Collections.Generic.ICollection\u00601[[HouseRentWebApi.ApplicationLogic.PropertyLogic.Model.PropertyGridModel, HouseRentWebApi.ApplicationLogic, Version=1.0.0.0, Culture=neutral, PublicKeyToken=null]]",
        "MediaTypes": [
          "text/plain",
          "application/json",
          "text/json"
        ],
        "StatusCode": 200
      }
    ]
  },
  {
    "ContainingType": "HouseRentWebApi.Controllers.PropertyController",
    "Method": "Upsert",
    "RelativePath": "api/Property/Upsert",
    "HttpMethod": "POST",
    "IsController": true,
    "Order": 0,
    "Parameters": [
      {
        "Name": "command",
        "Type": "HouseRentWebApi.ApplicationLogic.PropertyLogic.Command.UpsertPropertyCommand",
        "IsRequired": true
      }
    ],
    "ReturnTypes": [
      {
        "Type": "System.Int32",
        "MediaTypes": [
          "text/plain",
          "application/json",
          "text/json"
        ],
        "StatusCode": 200
      },
      {
        "Type": "Microsoft.AspNetCore.Mvc.ProblemDetails",
        "MediaTypes": [
          "text/plain",
          "application/json",
          "text/json"
        ],
        "StatusCode": 0
      }
    ]
  },
  {
    "ContainingType": "HouseRentWebApi.Controllers.PropertyTypeController",
    "Method": "Delete",
    "RelativePath": "api/PropertyType/Delete/{id}",
    "HttpMethod": "DELETE",
    "IsController": true,
    "Order": 0,
    "Parameters": [
      {
        "Name": "id",
        "Type": "System.Int32",
        "IsRequired": true
      }
    ],
    "ReturnTypes": [
      {
        "Type": "System.Int32",
        "MediaTypes": [
          "text/plain",
          "application/json",
          "text/json"
        ],
        "StatusCode": 200
      }
    ]
  },
  {
    "ContainingType": "HouseRentWebApi.Controllers.PropertyTypeController",
    "Method": "Get",
    "RelativePath": "api/PropertyType/Get/{id}",
    "HttpMethod": "GET",
    "IsController": true,
    "Order": 0,
    "Parameters": [
      {
        "Name": "id",
        "Type": "System.Int32",
        "IsRequired": true
      }
    ],
    "ReturnTypes": [
      {
        "Type": "HouseRentWebApi.ApplicationLogic.PropertyTypeLogic.Model.PropertyTypeViewModel",
        "MediaTypes": [
          "text/plain",
          "application/json",
          "text/json"
        ],
        "StatusCode": 200
      },
      {
        "Type": "Microsoft.AspNetCore.Mvc.ProblemDetails",
        "MediaTypes": [
          "text/plain",
          "application/json",
          "text/json"
        ],
        "StatusCode": 404
      }
    ]
  },
  {
    "ContainingType": "HouseRentWebApi.Controllers.PropertyTypeController",
    "Method": "GetAll",
    "RelativePath": "api/PropertyType/GetAll",
    "HttpMethod": "GET",
    "IsController": true,
    "Order": 0,
    "Parameters": [],
    "ReturnTypes": [
      {
        "Type": "System.Collections.Generic.ICollection\u00601[[HouseRentWebApi.ApplicationLogic.PropertyTypeLogic.Model.PropertyTypeGridModel, HouseRentWebApi.ApplicationLogic, Version=1.0.0.0, Culture=neutral, PublicKeyToken=null]]",
        "MediaTypes": [
          "text/plain",
          "application/json",
          "text/json"
        ],
        "StatusCode": 200
      }
    ]
  },
  {
    "ContainingType": "HouseRentWebApi.Controllers.PropertyTypeController",
    "Method": "Upsert",
    "RelativePath": "api/PropertyType/Upsert",
    "HttpMethod": "POST",
    "IsController": true,
    "Order": 0,
    "Parameters": [
      {
        "Name": "command",
        "Type": "HouseRentWebApi.ApplicationLogic.PropertyTypeLogic.Command.UpsertPropertyTypeCommand",
        "IsRequired": true
      }
    ],
    "ReturnTypes": [
      {
        "Type": "System.Int32",
        "MediaTypes": [
          "text/plain",
          "application/json",
          "text/json"
        ],
        "StatusCode": 200
      },
      {
        "Type": "Microsoft.AspNetCore.Mvc.ProblemDetails",
        "MediaTypes": [
          "text/plain",
          "application/json",
          "text/json"
        ],
        "StatusCode": 0
      }
    ]
  }
]